mentorstec/__init__.py
mentorstec/azure/__init__.py
mentorstec/azure/azure_service_bus_repository.py
mentorstec/dremio/__init__.py
mentorstec/dremio/dremio.py
mentorstec/eventhub/__init__.py
mentorstec/eventhub/event_hub.py
mentorstec/eventhub/event_hub_client.py
mentorstec/lakehouse/__init__.py
mentorstec/powerbi/__init__.py
mentorstec/powerbi/powerbi.py
mentorstec/repository/__init__.py
mentorstec/repository/dremio_repository.py
mentorstec/repository/eventhub_repository.py
mentorstec/repository/powerbi_repository.py
mentorstec-1.0.3.dist-info/METADATA
mentorstec-1.0.3.dist-info/WHEEL
mentorstec-1.0.3.dist-info/licenses/LICENSE
mentorstec-1.0.3.dist-info/RECORD
