Metadata-Version: 2.4
Name: mentorstec
Version: 1.0.3
Summary: Mentorstec - centralized event logging and monitoring
Project-URL: Homepage, https://github.com/Mentorstec/mentorstec
Project-URL: Repository, https://github.com/Mentorstec/mentorstec
Project-URL: Issues, https://github.com/Mentorstec/mentorstec/issues
Project-URL: Documentation, https://github.com/Mentorstec/mentorstec#readme
Author-email: Mentorstec <diego@mentorstec.com.br>
License-Expression: MIT
License-File: LICENSE
Keywords: azure,event-hub,exceptions,logging,mentorstec,monitoring
Classifier: Development Status :: 4 - Beta
Classifier: Intended Audience :: Developers
Classifier: License :: OSI Approved :: MIT License
Classifier: Operating System :: OS Independent
Classifier: Programming Language :: Python :: 3
Classifier: Programming Language :: Python :: 3.8
Classifier: Programming Language :: Python :: 3.9
Classifier: Programming Language :: Python :: 3.10
Classifier: Programming Language :: Python :: 3.11
Classifier: Programming Language :: Python :: 3.12
Classifier: Topic :: System :: Logging
Classifier: Topic :: System :: Monitoring
Requires-Python: >=3.8
Requires-Dist: azure-servicebus>=7.0.0
Requires-Dist: backports-zoneinfo>=0.2.1; python_version < '3.9'
Provides-Extra: dev
Requires-Dist: black; extra == 'dev'
Requires-Dist: build; extra == 'dev'
Requires-Dist: mypy; extra == 'dev'
Requires-Dist: pytest-cov; extra == 'dev'
Requires-Dist: pytest>=7.0; extra == 'dev'
Requires-Dist: ruff; extra == 'dev'
Requires-Dist: twine; extra == 'dev'
Provides-Extra: dremio
Requires-Dist: requests>=2.25.0; extra == 'dremio'
Provides-Extra: powerbi
Requires-Dist: adal>=1.2.0; extra == 'powerbi'
Requires-Dist: requests>=2.25.0; extra == 'powerbi'
